flekspy/__init__.py
flekspy/flekspy.py
flekspy/amrex/__init__.py
flekspy/amrex/particle_data.py
flekspy/amrex/plotting.py
flekspy/idl/__init__.py
flekspy/idl/idl.py
flekspy/plot/__init__.py
flekspy/plot/streamplot.py
flekspy/tp/__init__.py
flekspy/tp/debug_tp.py
flekspy/tp/test_particles.py
flekspy/util/__init__.py
flekspy/util/exosphere.py
flekspy/util/gmm.py
flekspy/util/logger.py
flekspy/util/safe_eval.py
flekspy/util/transformations.py
flekspy/util/utilities.py
flekspy/xarray/__init__.py
flekspy/xarray/accessor.py
flekspy/yt/__init__.py
flekspy/yt/yt.py
flekspy-0.7.3.dist-info/METADATA
flekspy-0.7.3.dist-info/WHEEL
flekspy-0.7.3.dist-info/licenses/LICENSE.md
flekspy-0.7.3.dist-info/RECORD
