Metadata-Version: 2.4
Name: flekspy
Version: 0.7.3
Summary: Python utilities for processing FLEKS data
Author-email: Yuxi Chen <yuxichen@umich.edu>, Hongyang Zhou <hyzhou@umich.edu>
License-File: LICENSE.md
Requires-Python: <3.14,>=3.10
Requires-Dist: numpy>=1.26.4
Requires-Dist: polars<1,>=0.20.21
Requires-Dist: requests<3,>=2.32.3
Requires-Dist: xarray>=2024.6.0
Requires-Dist: xugrid<1,>=0.14.2
Provides-Extra: dev
Requires-Dist: h5py<4,>=3.11.0; extra == 'dev'
Requires-Dist: jupyter<2,>=1.0.0; extra == 'dev'
Requires-Dist: matplotlib<4,>=3.8.2; extra == 'dev'
Requires-Dist: myst-nb<2,>=1.0.0; extra == 'dev'
Requires-Dist: pydata-sphinx-theme<1,>=0.15; extra == 'dev'
Requires-Dist: pytest-benchmark<5,>=4.0.0; extra == 'dev'
Requires-Dist: pytest-cov<5,>=4.1.0; extra == 'dev'
Requires-Dist: pytest<9,>=8.0.0; extra == 'dev'
Requires-Dist: scikit-learn<2,>=1.3.2; extra == 'dev'
Requires-Dist: scipy<2,>=1.14.1; extra == 'dev'
Requires-Dist: sphinx-autoapi<4,>=3.0.0; extra == 'dev'
Requires-Dist: sphinx-jupyterbook-latex<2,>=1.0; extra == 'dev'
Requires-Dist: yt<5,>=4.3.0; extra == 'dev'
Provides-Extra: docs
Requires-Dist: myst-nb<2,>=1.0.0; extra == 'docs'
Requires-Dist: pydata-sphinx-theme<1,>=0.15; extra == 'docs'
Requires-Dist: scikit-learn<2,>=1.3.2; extra == 'docs'
Requires-Dist: sphinx-autoapi<4,>=3.0.0; extra == 'docs'
Requires-Dist: sphinx-jupyterbook-latex<2,>=1.0; extra == 'docs'
Provides-Extra: hdf5
Requires-Dist: h5py<4,>=3.11.0; extra == 'hdf5'
Provides-Extra: ml
Requires-Dist: scikit-learn<2,>=1.3.2; extra == 'ml'
Provides-Extra: plot
Requires-Dist: matplotlib<4,>=3.8.2; extra == 'plot'
Requires-Dist: scipy<2,>=1.14.1; extra == 'plot'
Provides-Extra: yt
Requires-Dist: yt<5,>=4.3.0; extra == 'yt'
